{
    "bottom_shell_layers": "6",
    "enable_prime_tower": "1",
    "enable_support": "1",
    "flush_into_infill": "1",
    "from": "User",
    "gap_infill_speed": "15",
    "inherits": "0.20mm Standard @Creality Ender3",
    "initial_layer_infill_speed": "15",
    "inner_wall_speed": "65",
    "internal_solid_infill_speed": "30",
    "is_custom_defined": "0",
    "name": "Sovol_sv04 - PLA (0.4mm Nozzle + Extrude)",
    "outer_wall_speed": "45",
    "prime_tower_width": "30",
    "print_settings_id": "Sovol_sv04 - PLA (0.4mm Nozzle + Extrude)",
    "skirt_loops": "1",
    "sparse_infill_density": "20%",
    "sparse_infill_pattern": "cubic",
    "sparse_infill_speed": "75",
    "support_bottom_z_distance": "0.4",
    "support_critical_regions_only": "1",
    "support_style": "organic",
    "support_top_z_distance": "0.4",
    "support_type": "tree(manual)",
    "top_shell_layers": "6",
    "top_surface_speed": "15",
    "travel_speed": "100",
    "version": "1.7.0.0",
    "wall_loops": "3"
}
